hpc_campaign/__init__.py
hpc_campaign/__main__.py
hpc_campaign/cache.py
hpc_campaign/config.py
hpc_campaign/connector.py
hpc_campaign/genkey.py
hpc_campaign/hdf5_metadata.py
hpc_campaign/key.py
hpc_campaign/list.py
hpc_campaign/manager.py
hpc_campaign/manager_args.py
hpc_campaign/remote_config.yaml
hpc_campaign/taridx.py
hpc_campaign/upgrade.py
hpc_campaign/utils.py
hpc_campaign-0.6.0.dist-info/licenses/LICENSE
hpc_campaign-0.6.0.dist-info/METADATA
hpc_campaign-0.6.0.dist-info/WHEEL
hpc_campaign-0.6.0.dist-info/entry_points.txt
hpc_campaign-0.6.0.dist-info/top_level.txt
hpc_campaign-0.6.0.dist-info/RECORD
