Metadata-Version: 2.4
Name: hpc-campaign
Version: 0.6.0
Summary: Campaign management scripts for remote data access
Author-email: Norbert Podhorszki <pnorbert@ornl.gov>
License-Expression: Apache-2.0
Project-URL: Source, https://github.com/ornladios/hpc-campaign
Project-URL: Tracker, https://github.com/ornladios/hpc-campaign/issues
Project-URL: Documentation, https://hpc-campaign.readthedocs.io/en/latest/
Keywords: campaign,remote data,adios2,hdf5
Classifier: Development Status :: 3 - Alpha
Classifier: Intended Audience :: Science/Research
Classifier: Intended Audience :: Education
Classifier: Intended Audience :: Developers
Classifier: Natural Language :: English
Classifier: Operating System :: POSIX :: Linux
Classifier: Programming Language :: Python :: 3.10
Classifier: Programming Language :: Python :: 3.11
Classifier: Programming Language :: Python :: 3.12
Classifier: Programming Language :: Python :: 3.13
Classifier: Topic :: Scientific/Engineering :: Visualization
Requires-Python: >=3.8
License-File: LICENSE
Requires-Dist: PyYAML>=6
Requires-Dist: paramiko>=3.5
Requires-Dist: PyNaCl>=1.5
Requires-Dist: redis>=5
Requires-Dist: h5py>=3.10
Requires-Dist: pillow>=11
Dynamic: license-file
